{
  "data": [
    {
      "id": 385590937,
      "name": "AppRepositories",
      "owner": {
        "login": "JoelPB",
        "avatar_url": "https://avatars.githubusercontent.com/u/29235472?v=4"
      },
      "html_url": "https://github.com/JoelPB/AppRepositories",
      "description": "description",
      "stargazers_count": 0,
      "language": "Kotlin"
    },
    {
      "id": 384746648,
      "name": "BusinessCard",
      "owner": {
        "login": "JoelPB",
        "avatar_url": "https://avatars.githubusercontent.com/u/29235472?v=4"
      },
      "html_url": "https://github.com/JoelPB/BusinessCard",
      "description": "description",
      "stargazers_count": 0,
      "language": "Kotlin"
    },
    {
      "id": 319405454,
      "name": "Criptomoeda",
      "owner": {
        "login": "JoelPB",
        "avatar_url": "https://avatars.githubusercontent.com/u/29235472?v=4"
      },
      "html_url": "https://github.com/JoelPB/Criptomoeda",
      "description": "Requisitando dados de uma API de criptomoedas, conforme o solicitado no curso da Digital Innovation One.",
      "stargazers_count": 0,
      "language": "JavaScript"
    },
    {
      "id": 381851735,
      "name": "Dados_Python_Pandas",
      "owner": {
        "login": "JoelPB",
        "avatar_url": "https://avatars.githubusercontent.com/u/29235472?v=4"
      },
      "html_url": "https://github.com/JoelPB/Dados_Python_Pandas",
      "description": "description",
      "stargazers_count": 0,
      "language": "Jupyter Notebook"
    },
    {
      "id": 330244753,
      "name": "dino-game",
      "owner": {
        "login": "JoelPB",
        "avatar_url": "https://avatars.githubusercontent.com/u/29235472?v=4"
      },
      "html_url": "https://github.com/JoelPB/dino-game",
      "description": "description",
      "stargazers_count": 0,
      "language": "JavaScript"
    },
    {
      "id": 336548365,
      "name": "DIO.Series",
      "owner": {
        "login": "JoelPB",
        "avatar_url": "https://avatars.githubusercontent.com/u/29235472?v=4"
      },
      "html_url": "https://github.com/JoelPB/DIO.Series",
      "description": "description",
      "stargazers_count": 0,
      "language": "C#"
    },
    {
      "id": 293369446,
      "name": "forca",
      "owner": {
        "login": "JoelPB",
        "avatar_url": "https://avatars.githubusercontent.com/u/29235472?v=4"
      },
      "html_url": "https://github.com/JoelPB/forca",
      "description": "O simples jogo da forca com utilização da dataFrame para armazenar os nomes",
      "stargazers_count": 0,
      "language": "Python"
    },
    {
      "id": 340991392,
      "name": "GENESIS",
      "owner": {
        "login": "JoelPB",
        "avatar_url": "https://avatars.githubusercontent.com/u/29235472?v=4"
      },
      "html_url": "https://github.com/JoelPB/GENESIS",
      "description": "Projeto para o curso da Digital Innovation One",
      "stargazers_count": 0,
      "language": "JavaScript"
    },
    {
      "id": 303217524,
      "name": "ivai",
      "owner": {
        "login": "JoelPB",
        "avatar_url": "https://avatars.githubusercontent.com/u/29235472?v=4"
      },
      "html_url": "https://github.com/JoelPB/ivai",
      "description": "Labirinto que necessita transpor barreiras, testando apenas algumas funcionalidades do pygame",
      "stargazers_count": 0,
      "language": "Python"
    },
    {
      "id": 340654490,
      "name": "jogo1",
      "owner": {
        "login": "JoelPB",
        "avatar_url": "https://avatars.githubusercontent.com/u/29235472?v=4"
      },
      "html_url": "https://github.com/JoelPB/jogo1",
      "description": "description",
      "stargazers_count": 0,
      "language": "JavaScript"
    }
    ]
}